README.md
setup.py
EDIunplugged/__init__.py
EDIunplugged/main.py
EDIunplugged/metrics.py
EDIunplugged/version.py
EDIunplugged.egg-info/PKG-INFO
EDIunplugged.egg-info/SOURCES.txt
EDIunplugged.egg-info/dependency_links.txt
EDIunplugged.egg-info/requires.txt
EDIunplugged.egg-info/top_level.txt