Metadata-Version: 1.0
Name: EDIunplugged
Version: 0.1.3
Summary: An algorithm to identifies false positive transit signals using TLS information
Home-page: https://github.com/jonzink/EDI_Vetter_unplugged
Author: Jon Zink
Author-email: jzink@astro.ucla.edu
License: MIT
Platform: UNKNOWN
